pytest_flask_sqlalchemy/__init__.py
pytest_flask_sqlalchemy/fixtures.py
pytest_flask_sqlalchemy/plugin.py
pytest_flask_sqlalchemy-1.1.0.dist-info/LICENSE
pytest_flask_sqlalchemy-1.1.0.dist-info/METADATA
pytest_flask_sqlalchemy-1.1.0.dist-info/WHEEL
pytest_flask_sqlalchemy-1.1.0.dist-info/entry_points.txt
pytest_flask_sqlalchemy-1.1.0.dist-info/top_level.txt
pytest_flask_sqlalchemy-1.1.0.dist-info/RECORD
