Metadata-Version: 2.1
Name: pytest-flask-sqlalchemy
Version: 1.1.0
Summary: A pytest plugin for preserving test isolation in Flask-SQlAlchemy using database transactions.
Home-page: https://github.com/jeancochrane/pytest-flask-sqlalchemy
Author: Jean Cochrane
Author-email: jean@jeancochrane.com
License: MIT
Platform: UNKNOWN
Classifier: Development Status :: 4 - Beta
Classifier: Environment :: Plugins
Classifier: Environment :: Web Environment
Classifier: Intended Audience :: Developers
Classifier: License :: OSI Approved :: MIT License
Classifier: Programming Language :: Python
Classifier: Topic :: Software Development :: Testing
Classifier: Topic :: Software Development :: Libraries :: Python Modules
Classifier: Framework :: Pytest
Provides-Extra: tests
License-File: LICENSE
